desired_state/__init__.py
desired_state/cli.py
desired_state/client.py
desired_state/collection.py
desired_state/control.py
desired_state/control_fsm.py
desired_state/desired_state.py
desired_state/diff.py
desired_state/messages.py
desired_state/monitor.py
desired_state/reconciliation_fsm.py
desired_state/rule.py
desired_state/server.py
desired_state/server_fsm.py
desired_state/stream.py
desired_state/types.py
desired_state/util.py
desired_state/validate.py
desired_state-0.1.0.dist-info/AUTHORS.rst
desired_state-0.1.0.dist-info/LICENSE
desired_state-0.1.0.dist-info/METADATA
desired_state-0.1.0.dist-info/WHEEL
desired_state-0.1.0.dist-info/entry_points.txt
desired_state-0.1.0.dist-info/top_level.txt
desired_state-0.1.0.dist-info/RECORD
