Metadata-Version: 2.1
Name: desired-state
Version: 0.1.0
Summary: A desired state system for ansible
Home-page: https://github.com/benthomasson/desired_state
Author: Ben Thomasson
Author-email: bthomass@redhat.com
License: Apache Software License 2.0
Keywords: desired_state
Platform: UNKNOWN
Classifier: Development Status :: 2 - Pre-Alpha
Classifier: Intended Audience :: Developers
Classifier: License :: OSI Approved :: Apache Software License
Classifier: Natural Language :: English
Classifier: Programming Language :: Python :: 3
Classifier: Programming Language :: Python :: 3.5
Classifier: Programming Language :: Python :: 3.6
Classifier: Programming Language :: Python :: 3.7
Classifier: Programming Language :: Python :: 3.8
Requires-Python: >=3.5
